Metadata-Version: 2.1
Name: waving_hands
Version: 0.1.1
Summary: P2P Multiplayer Python implementation of Richard Bartle's Waving Hands
Home-page: https://github.com/alanb33/WavingHands
Author: Alan Bailey
Author-email: 
License: GNUv3
Keywords: waving hands turnbased
Classifier: Development Status :: 3 - Alpha
Classifier: Environment :: Console
Classifier: Framework :: Pytest
Classifier: Intended Audience :: End Users/Desktop
Classifier: License :: OSI Approved :: GNU General Public License v3 (GPLv3)
Classifier: Natural Language :: English
Classifier: Operating System :: OS Independent
Classifier: Programming Language :: Python :: 3
Classifier: Topic :: Games/Entertainment :: Turn Based Strategy
License-File: LICENSE
